flask_formation/__init__.py
flask_formation/class_helpers.py
flask_formation/dictionary_helpers.py
flask_formation/enum.py
flask_formation/exception.py
flask_formation/field.py
flask_formation/string_helpers.py
flask_formation/type.py
flask_formation/widget.py
flask_formation-2.0.0.dist-info/LICENSE
flask_formation-2.0.0.dist-info/METADATA
flask_formation-2.0.0.dist-info/WHEEL
flask_formation-2.0.0.dist-info/top_level.txt
flask_formation-2.0.0.dist-info/RECORD
