Metadata-Version: 2.2
Name: flask_formation
Version: 2.0.0
Summary: Sub package for flask-wtf forms
Author-email: Tyler Petrov <tylerpetrov16@gmail.com>
Project-URL: Homepage, https://github.com/Tyler-Petrov/flask_formation
Project-URL: Issues, https://github.com/Tyler-Petrov/flask_formation/issues
Classifier: Programming Language :: Python :: 3
Classifier: License :: OSI Approved :: MIT License
Classifier: Operating System :: OS Independent
Requires-Python: >=3.6
License-File: LICENSE
